tgchequeman/AppleColorEmoji.ttf
tgchequeman/__init__.py
tgchequeman/exceptions.py
tgchequeman/utils.py
tgchequeman/version.py
tgchequeman-0.0.8.dist-info/LICENSE
tgchequeman-0.0.8.dist-info/METADATA
tgchequeman-0.0.8.dist-info/WHEEL
tgchequeman-0.0.8.dist-info/top_level.txt
tgchequeman-0.0.8.dist-info/RECORD
